onglai-classify-homologues/__init__.py
onglai-classify-homologues/nextgen_classify_homols.py
onglai-classify-homologues/prototype-streamlit.py
onglai-classify-homologues/utils.py
tests/__init__.py
tests/test_io.py
onglai_classify_homologues-1.0.0.dist-info/LICENSE
onglai_classify_homologues-1.0.0.dist-info/METADATA
onglai_classify_homologues-1.0.0.dist-info/WHEEL
onglai_classify_homologues-1.0.0.dist-info/top_level.txt
onglai_classify_homologues-1.0.0.dist-info/RECORD
