Metadata-Version: 2.1
Name: onglai-classify-homologues
Version: 1.0.0
Summary: A cheminformatics algorithm to classify homologous series.
Home-page: https://github.com/adelenelai/onglai-classify-homologues
Author: Adelene Lai
Author-email: adelene.lai@uni.lu
Maintainer: Adelene Lai
Maintainer-email: adelene.lai@uni.lu
License: Apache
Classifier: Programming Language :: Python :: 3
Classifier: Programming Language :: Python :: 3.5
Classifier: Programming Language :: Python :: 3.6
Classifier: Programming Language :: Python :: 3.7
Classifier: Programming Language :: Python :: 3.8
Classifier: Programming Language :: Python :: 3.9
Classifier: Programming Language :: Python :: 3.10
Classifier: Programming Language :: Python :: 3 :: Only
Classifier: License :: OSI Approved :: Apache Software License
Classifier: Operating System :: OS Independent
Requires-Python: >=3.5
License-File: LICENSE
Requires-Dist: pandas
Requires-Dist: numpy
Requires-Dist: matplotlib
Requires-Dist: pytest
Requires-Dist: rdkit
Requires-Dist: datamol
